awsdeployer/__init__.py
awsdeployer/__status_dict.py
awsdeployer/__util.py
awsdeployer/exceptions.py
awsdeployer/gatewayres.py
awsdeployer/status.py
awsdeployer/__apigateway/GatewayHandler.py
awsdeployer/__apigateway/Templater.py
awsdeployer/__apigateway/Wrapper.py
awsdeployer/__apigateway/__init__.py
awsdeployer/__lambdas/FunctionHandler.py
awsdeployer/__lambdas/IamHandler.py
awsdeployer/__lambdas/LayerHandler.py
awsdeployer/__lambdas/__init__.py
awsdeployer-1.15.1.data/scripts/apigateway
awsdeployer-1.15.1.data/scripts/lambda
awsdeployer-1.15.1.dist-info/LICENSE
awsdeployer-1.15.1.dist-info/METADATA
awsdeployer-1.15.1.dist-info/WHEEL
awsdeployer-1.15.1.dist-info/top_level.txt
awsdeployer-1.15.1.dist-info/RECORD
