Metadata-Version: 2.1
Name: awsdeployer
Version: 1.15.1
Summary: Collection of some scripts to automate AWS Lambda and API Gateway deployments
Home-page: https://github.com/sgtpepperpt/awsdeployer
Author: Guilherme Borges
Author-email: guilherme@guilhermeborges.net
License: UNKNOWN
Platform: UNKNOWN
Classifier: Programming Language :: Python :: 3
Classifier: License :: OSI Approved :: GNU General Public License v3 (GPLv3)
Classifier: Operating System :: OS Independent
Requires-Python: >=3.8
Requires-Dist: boto3
Requires-Dist: configparser
